codingame/__init__.py
codingame/abc.py
codingame/clash_of_code.py
codingame/codingamer.py
codingame/exceptions.py
codingame/leaderboard.py
codingame/state.py
codingame/utils.py
codingame/client/__init__.py
codingame/client/async_.py
codingame/client/base.py
codingame/client/client.py
codingame/client/sync.py
codingame/http/__init__.py
codingame/http/async_.py
codingame/http/base.py
codingame/http/client.py
codingame/http/httperror.py
codingame/http/sync.py
codingame/notification/__init__.py
codingame/notification/data.py
codingame/notification/enums.py
codingame/notification/notification.py
codingame/types/__init__.py
codingame/types/clash_of_code.py
codingame/types/codingamer.py
codingame/types/notification.py
codingame-1.4.3.dist-info/LICENSE
codingame-1.4.3.dist-info/METADATA
codingame-1.4.3.dist-info/WHEEL
codingame-1.4.3.dist-info/top_level.txt
codingame-1.4.3.dist-info/RECORD
