Metadata-Version: 2.1
Name: codingame
Version: 1.4.3
Summary: Pythonic wrapper for the undocumented CodinGame API.
Home-page: https://github.com/takos22/codingame
Author: takos22
Author-email: takos2210@gmail.com
License: MIT
Project-URL: Documentation, https://codingame.readthedocs.io/
Project-URL: Issue tracker, https://github.com/takos22/codingame/issues
Classifier: Programming Language :: Python
Classifier: Programming Language :: Python :: 3
Classifier: Programming Language :: Python :: 3 :: Only
Classifier: Programming Language :: Python :: 3.8
Classifier: Programming Language :: Python :: 3.9
Classifier: Programming Language :: Python :: 3.10
Classifier: Programming Language :: Python :: 3.11
Classifier: Programming Language :: Python :: 3.12
Requires-Python: >=3.8
License-File: LICENSE
Requires-Dist: requests ~=2.25
Provides-Extra: async
Requires-Dist: aiohttp ~=3.7 ; extra == 'async'
